Metadata-Version: 2.1
Name: automagicio
Version: 1.0.0
Summary: A versatile plugin module for streamlining input/output operations in Python projects.
Home-page: https://github.com/ishanoshada/automagicio
Author: Ishan Oshada
Author-email: ic31908@gamil.com
License: UNKNOWN
Keywords: auto,magic,io,file handling,data transformation
Platform: UNKNOWN
Classifier: Programming Language :: Python :: 3
Classifier: License :: OSI Approved :: MIT License
Classifier: Operating System :: OS Independent
